bnw_tools/__init__.py
bnw_tools/__main__.py
bnw_tools/ORKG/__init__.py
bnw_tools/ORKG/bibtex_to_csv.py
bnw_tools/core/__init__.py
bnw_tools/core/helper.py
bnw_tools/extract/__init__.py
bnw_tools/extract/extract_from_html.py
bnw_tools/extract/util_pdf.py
bnw_tools/extract/util_pytube.py
bnw_tools/extract/util_whisper.py
bnw_tools/extract/util_zotero.py
bnw_tools/extract/nlp/__init__.py
bnw_tools/extract/nlp/my_stop_words.py
bnw_tools/extract/nlp/nlp.py
bnw_tools/extract/nlp/util_nlp.py
bnw_tools/extract/nlp/util_stanza.py
bnw_tools/publish/__init__.py
bnw_tools/publish/createVTT.py
bnw_tools/publish/graphvizify.py
bnw_tools/publish/util_networkx.py
bnw_tools/publish/util_pyplot.py
bnw_tools/publish/util_wordcloud.py
bnw_tools/publish/LaTeX/__init__.py
bnw_tools/publish/LaTeX/texify.py
bnw_tools/publish/MediaWiki/__init__.py
bnw_tools/publish/MediaWiki/mediaWiki.py
bnw_tools/publish/MediaWiki/playlist2wiki-converter.py
bnw_tools/publish/MediaWiki/wiki_bot.py
bnw_tools/publish/MediaWiki/wiki/__init__.py
bnw_tools/publish/MediaWiki/wiki/barlow.py
bnw_tools/publish/MediaWiki/wiki/main.py
bnw_tools/publish/Obsidian/README.md
bnw_tools/publish/Obsidian/__init__.py
bnw_tools/publish/Obsidian/bibtex_to_notes.py
bnw_tools/publish/Obsidian/nlped_whispered_folder.py
bnw_tools/publish/Obsidian/obsidize.py
bnw_tools/publish/Obsidian/transitions.py
bnw_tools/review/__init__.py
bnw_tools/review/k_score.py
bnw_tools/review/similarity.py
bnw_tools/review/spellcheck.py
bnw_tools/review/util_wordfreq.py
bnw_tools/review/library/__init__.py
bnw_tools/review/library/barlow.py
bnw_tools/review/library/main.py
bnw_tools/ORKG/RF_Map.json
bnw_tools/ORKG/ResearchFields.json
bnw_tools-0.0.2.0.dist-info/METADATA
bnw_tools-0.0.2.0.dist-info/WHEEL
bnw_tools-0.0.2.0.dist-info/licenses/LICENSE
bnw_tools-0.0.2.0.dist-info/RECORD
