Metadata-Version: 2.3
Name: bnw_tools
Version: 0.0.2.0
Summary: Tools developed in the BorgNetzWerk project for the extraction, analysis and publication of knowledge.
Project-URL: Homepage, https://borgnetzwerk.de/
Project-URL: Repository, https://github.com/borgnetzwerk/tools
Project-URL: Issues, https://github.com/borgnetzwerk/tools/issues
Author-email: BorgNetzWerk <info@borgnetzwerk.de>, Tim Wittenborg <tim.wittenborg@l3s.uni-hannover.de>
License-File: LICENSE
Keywords: BorgNetzWerk,ORKG,knowledge,literature,media
Classifier: License :: OSI Approved :: MIT License
Classifier: Operating System :: OS Independent
Classifier: Programming Language :: Python :: 3
Requires-Python: <3.12,>=3.8
Requires-Dist: bibtexparser
Requires-Dist: flair
Requires-Dist: jupyter
Requires-Dist: levenshtein
Requires-Dist: mutagen
Requires-Dist: opencv-python
Requires-Dist: pandas
Requires-Dist: path
Requires-Dist: pdfminer
Requires-Dist: pdfminer-six
Requires-Dist: pdfquery
Requires-Dist: pdfrw
Requires-Dist: pymupdf
Requires-Dist: pypdf2
Requires-Dist: pyyaml
Requires-Dist: scipy==1.10.1
Requires-Dist: spacy<4.0.0,>=3.0.0
Requires-Dist: termcolor
Requires-Dist: wordcloud
Requires-Dist: wordfreq
Provides-Extra: whisper
Requires-Dist: openai-whisper; extra == 'whisper'
Provides-Extra: youtube
Requires-Dist: pytube; extra == 'youtube'
